mfd_osd_control/__init__.py
mfd_osd_control/exceptions.py
mfd_osd_control/mfd_osd_control.py
mfd_osd_control-0.9.0.dist-info/licenses/AUTHORS.md
mfd_osd_control-0.9.0.dist-info/licenses/LICENSE.md
mfd_osd_control-0.9.0.dist-info/METADATA
mfd_osd_control-0.9.0.dist-info/WHEEL
mfd_osd_control-0.9.0.dist-info/top_level.txt
mfd_osd_control-0.9.0.dist-info/RECORD
