Metadata-Version: 2.4
Name: mfd-osd-control
Version: 0.9.0
Summary: Module for controlling entries in OSD.
Project-URL: Homepage, https://github.com/intel/mfd
Project-URL: Repository, https://github.com/intel/mfd-osd-control
Project-URL: Issues, https://github.com/intel/mfd-osd-control/issues
Project-URL: Changelog, https://github.com/intel/mfd-osd-control/blob/main/CHANGELOG.md
Requires-Python: <3.14,>=3.10
License-File: LICENSE.md
License-File: AUTHORS.md
Requires-Dist: requests<3,>=2.27.0
Requires-Dist: mfd_common_libs>=1.11.0
Dynamic: license-file
